anal/__init__.py
anal/auth/__init__.py
anal/auth/backends.py
anal/auth/decorators.py
anal/auth/middleware.py
anal/auth/models.py
anal/cli/__init__.py
anal/cli/__main__.py
anal/cli/main.py
anal/cli/commands/__init__.py
anal/cli/commands/createuser.py
anal/cli/commands/makemigrations.py
anal/cli/commands/migrate.py
anal/cli/commands/migration.py
anal/cli/commands/runserver.py
anal/cli/commands/runserver_new.py
anal/cli/commands/shell.py
anal/cli/commands/startapp.py
anal/cli/commands/startproject.py
anal/cli/commands/user.py
anal/core/__init__.py
anal/core/application.py
anal/core/config.py
anal/core/container.py
anal/core/events.py
anal/core/exceptions.py
anal/core/registry.py
anal/db/__init__.py
anal/db/connection.py
anal/db/managers.py
anal/db/migrations.py
anal/db/models.py
anal/http/__init__.py
anal/http/controllers.py
anal/http/middleware.py
anal/http/responses.py
anal/http/routing.py
anal_framework-0.1.0.dist-info/licenses/LICENSE
anal_framework-0.1.0.dist-info/METADATA
anal_framework-0.1.0.dist-info/WHEEL
anal_framework-0.1.0.dist-info/entry_points.txt
anal_framework-0.1.0.dist-info/top_level.txt
anal_framework-0.1.0.dist-info/RECORD
