Metadata-Version: 2.4
Name: anal-framework
Version: 0.1.0
Summary: Advanced Network Application Layer - A modern Python backend framework
Author-email: ANAL Framework Team <team@analframework.org>
Maintainer-email: ANAL Framework Team <team@analframework.org>
License-Expression: MIT
Project-URL: Homepage, https://github.com/analframework/anal
Project-URL: Documentation, https://docs.analframework.org
Project-URL: Repository, https://github.com/analframework/anal
Project-URL: Bug Tracker, https://github.com/analframework/anal/issues
Project-URL: Changelog, https://github.com/analframework/anal/blob/main/CHANGELOG.md
Keywords: web,framework,backend,api,async,orm,rest,graphql
Classifier: Development Status :: 3 - Alpha
Classifier: Intended Audience :: Developers
Classifier: Operating System :: OS Independent
Classifier: Programming Language :: Python :: 3
Classifier: Programming Language :: Python :: 3.12
Classifier: Programming Language :: Python :: 3.13
Classifier: Framework :: AsyncIO
Classifier: Topic :: Internet :: WWW/HTTP :: WSGI :: Application
Classifier: Topic :: Software Development :: Libraries :: Application Frameworks
Classifier: Topic :: Software Development :: Libraries :: Python Modules
Requires-Python: >=3.12
License-File: LICENSE
Requires-Dist: uvicorn[standard]>=0.24.0
Requires-Dist: starlette>=0.32.0
Requires-Dist: pydantic>=2.5.0
Requires-Dist: SQLAlchemy[asyncio]>=2.0.0
Requires-Dist: alembic>=1.13.0
Requires-Dist: asyncpg>=0.29.0
Requires-Dist: aiomysql>=0.2.0
Requires-Dist: aiosqlite>=0.19.0
Requires-Dist: motor>=3.3.0
Requires-Dist: redis[hiredis]>=5.0.0
Requires-Dist: jinja2>=3.1.0
Requires-Dist: python-multipart>=0.0.6
Requires-Dist: python-jose[cryptography]>=3.3.0
Requires-Dist: passlib[bcrypt]>=1.7.4
Requires-Dist: python-dotenv>=1.0.0
Requires-Dist: click>=8.1.0
Requires-Dist: rich>=13.7.0
Requires-Dist: typer>=0.9.0
Requires-Dist: httpx>=0.25.0
Requires-Dist: websockets>=12.0
Requires-Dist: celery[redis]>=5.3.0
Requires-Dist: pydantic-settings>=2.1.0
Requires-Dist: email-validator>=2.1.0
Requires-Dist: cryptography>=41.0.0
Requires-Dist: aiofiles>=23.2.1
Requires-Dist: orjson>=3.9.0
Requires-Dist: graphene>=3.3.0
Requires-Dist: strawberry-graphql>=0.215.0
Provides-Extra: dev
Requires-Dist: pytest>=7.4.0; extra == "dev"
Requires-Dist: pytest-asyncio>=0.23.0; extra == "dev"
Requires-Dist: pytest-cov>=4.1.0; extra == "dev"
Requires-Dist: black>=23.12.0; extra == "dev"
Requires-Dist: isort>=5.13.0; extra == "dev"
Requires-Dist: flake8>=6.1.0; extra == "dev"
Requires-Dist: mypy>=1.8.0; extra == "dev"
Requires-Dist: pre-commit>=3.6.0; extra == "dev"
Requires-Dist: sphinx>=7.2.0; extra == "dev"
Requires-Dist: sphinx-rtd-theme>=2.0.0; extra == "dev"
Requires-Dist: coverage>=7.4.0; extra == "dev"
Provides-Extra: docs
Requires-Dist: mkdocs>=1.5.0; extra == "docs"
Requires-Dist: mkdocs-material>=9.5.0; extra == "docs"
Requires-Dist: mkdocstrings[python]>=0.24.0; extra == "docs"
Provides-Extra: postgres
Requires-Dist: asyncpg>=0.29.0; extra == "postgres"
Provides-Extra: mysql
Requires-Dist: aiomysql>=0.2.0; extra == "mysql"
Provides-Extra: mongodb
Requires-Dist: motor>=3.3.0; extra == "mongodb"
Provides-Extra: all
Requires-Dist: ANAL[dev,docs,mongodb,mysql,postgres]; extra == "all"
Dynamic: license-file
